{"name": "Muhamad Khairul Rosyidy Damaji", "mobile": "087711590743", "email": "khairulnajwa1@gmail.com", "skills": ["GIS & Remote Sensing", "ArcGIS", "QGIS", "Google Earth Engine", "Google Colab", "Jupyter Notebook", "Drone/UAV", "Python", "JavaScript", "R (basic)", "SharePoint", "WebGIS Dashboard", "LULC", "Deformation", "Deforestation", "Plant Health", "Leadership/Team Management", "Sustainability", "Public Speaking", "Analytical Thinking"], "experience_years": "4+", "education_1": "Bachelor of Science in Geography, Faculty of Mathematics and Natural Sciences, Universitas Indonesia, Depok, Indonesia, GPA: 3.68 (Cum Laude)", "education_2": "", "certifications": "", "linkedin": "www.linkedin.com/in/mkhairulrosyidy", "suitable": "Yes", "conclusion": "The candidate meets the requirement with a Bachelor's Degree in Geography, which is closely related to the specified fields. They have 4+ years of experience coordinating GIS projects with remote sensing data, exceeding the minimum requirement. While the specific certification SKKNI IG Level 7 in Remote Sensing/GIS sub-field is preferred, the candidate's skills and experience make them a strong fit for the role."}